opposablethumbs
