Metadata-Version: 1.0
Name: django-opposable-thumbs
Version: 0.0.10
Summary: Easy image manipulation for Django
Home-page: https://github.com/joncombe/django-opposable-thumbs
Author: Jon Combe
Author-email: pypi@joncombe.net
License: BSD licence, see LICENCE file
Platform: UNKNOWN
